Metadata-Version: 1.0
Name: shahz-probability
Version: 0.1
Summary: Gaussian and Binomial distributions
Home-page: UNKNOWN
Author: shah bhatti
Author-email: cleashahbhatti@gmail.com
License: UNKNOWN
Platform: UNKNOWN
